aldryn_snippet/__init__.py
aldryn_snippet/cms_plugins.py
aldryn_snippet/forms.py
aldryn_snippet/models.py
aldryn_snippet/tests.py
aldryn_snippet/management/__init__.py
aldryn_snippet/management/commands/__init__.py
aldryn_snippet/management/commands/migrate_from_djangocms_snippet.py
aldryn_snippet/migrations/0001_initial.py
aldryn_snippet/migrations/__init__.py
aldryn_snippet/south_migrations/0001_initial.py
aldryn_snippet/south_migrations/0002_auto__add_snippetplugin.py
aldryn_snippet/south_migrations/0003_auto__add_field_snippetplugin_name.py
aldryn_snippet/south_migrations/__init__.py
aldryn_snippet/static/js/ace-1.1.7/ace.js
aldryn_snippet/static/js/ace-1.1.7/mode-css.js
aldryn_snippet/static/js/ace-1.1.7/mode-html.js
aldryn_snippet/static/js/ace-1.1.7/mode-javascript.js
aldryn_snippet/static/js/ace-1.1.7/mode-text.js
aldryn_snippet/static/js/ace-1.1.7/theme-ambiance.js
aldryn_snippet/static/js/ace-1.1.7/theme-chaos.js
aldryn_snippet/static/js/ace-1.1.7/theme-chrome.js
aldryn_snippet/static/js/ace-1.1.7/theme-clouds.js
aldryn_snippet/static/js/ace-1.1.7/theme-clouds_midnight.js
aldryn_snippet/static/js/ace-1.1.7/theme-cobalt.js
aldryn_snippet/static/js/ace-1.1.7/theme-crimson_editor.js
aldryn_snippet/static/js/ace-1.1.7/theme-dawn.js
aldryn_snippet/static/js/ace-1.1.7/theme-dreamweaver.js
aldryn_snippet/static/js/ace-1.1.7/theme-eclipse.js
aldryn_snippet/static/js/ace-1.1.7/theme-github.js
aldryn_snippet/static/js/ace-1.1.7/theme-idle_fingers.js
aldryn_snippet/static/js/ace-1.1.7/theme-katzenmilch.js
aldryn_snippet/static/js/ace-1.1.7/theme-kr.js
aldryn_snippet/static/js/ace-1.1.7/theme-kr_theme.js
aldryn_snippet/static/js/ace-1.1.7/theme-kuroir.js
aldryn_snippet/static/js/ace-1.1.7/theme-merbivore.js
aldryn_snippet/static/js/ace-1.1.7/theme-merbivore_soft.js
aldryn_snippet/static/js/ace-1.1.7/theme-mono_industrial.js
aldryn_snippet/static/js/ace-1.1.7/theme-monokai.js
aldryn_snippet-0.1.4.2.dist-info/DESCRIPTION.rst
aldryn_snippet-0.1.4.2.dist-info/METADATA
aldryn_snippet-0.1.4.2.dist-info/RECORD
aldryn_snippet-0.1.4.2.dist-info/WHEEL
aldryn_snippet-0.1.4.2.dist-info/metadata.json
aldryn_snippet-0.1.4.2.dist-info/top_level.txt
