Metadata-Version: 2.0
Name: aldryn-snippet
Version: 0.1.4.2
Summary: Snippets
Home-page: https://github.com/aldryn/aldryn-snippet
Author: Divio AG
Author-email: info@divio.ch
License: LICENSE.txt
Platform: OS Independent
Classifier: Development Status :: 2 - Pre-Alpha
Classifier: Environment :: Web Environment
Classifier: Framework :: Django
Classifier: Intended Audience :: Developers
Classifier: License :: OSI Approved :: BSD License
Classifier: Operating System :: OS Independent
Classifier: Programming Language :: Python
Classifier: Topic :: Internet :: WWW/HTTP :: Dynamic Content
Classifier: Topic :: Software Development
Classifier: Topic :: Software Development :: Libraries :: Application Frameworks
Requires-Dist: django-cms (>=3.0,<3.3)
Requires-Dist: django-mptt (>=0.6,<0.9)
Requires-Dist: djangocms-snippet (>=1.4,<1.8)
